helix/Home.py
helix/__init__.py
helix/launch.py
helix/.streamlit/config.toml
helix/components/__init__.py
helix/components/configuration.py
helix/components/experiments.py
helix/components/logs.py
helix/components/plot_editor.py
helix/components/plots.py
helix/components/preprocessing.py
helix/components/statistical_tests.py
helix/components/forms/__init__.py
helix/components/forms/forms_fi.py
helix/components/forms/forms_ml_opts.py
helix/components/forms/forms_plots.py
helix/components/forms/forms_preprocessing.py
helix/components/images/__init__.py
helix/components/images/logos.py
helix/feature_importance/feature_importance.py
helix/feature_importance/fuzzy.py
helix/feature_importance/fuzzy_interpretation.py
helix/feature_importance/interpreter.py
helix/machine_learning/learner.py
helix/machine_learning/train.py
helix/machine_learning/models/BRNNs.py
helix/machine_learning/models/__init__.py
helix/machine_learning/models/mlrem.py
helix/machine_learning/models/random_forest.py
helix/machine_learning/models/svm.py
helix/options/__init__.py
helix/options/data.py
helix/options/enums.py
helix/options/execution.py
helix/options/fi.py
helix/options/file_paths.py
helix/options/fuzzy.py
helix/options/ml.py
helix/options/plotting.py
helix/options/preprocessing.py
helix/options/search_grids.py
helix/options/choices/__init__.py
helix/options/choices/metrics.py
helix/options/choices/ml_models.py
helix/options/choices/ui.py
helix/pages/1_New_Experiment.py
helix/pages/2_Data_Preprocessing.py
helix/pages/3_Data_Visualisation.py
helix/pages/4_Train_Models.py
helix/pages/5_Feature_Importance.py
helix/pages/6_Predict.py
helix/pages/7_View_Experiments.py
helix/pages/__init__.py
helix/preprocessing/feature_selection.py
helix/preprocessing/variable_scaling.py
helix/services/__init__.py
helix/services/configuration.py
helix/services/data.py
helix/services/experiments.py
helix/services/logs.py
helix/services/metrics.py
helix/services/ml_models.py
helix/services/plotting.py
helix_ai-1.0.4.dist-info/METADATA
helix_ai-1.0.4.dist-info/WHEEL
helix_ai-1.0.4.dist-info/entry_points.txt
helix_ai-1.0.4.dist-info/licenses/LICENSE
helix_ai-1.0.4.dist-info/RECORD
