Metadata-Version: 2.4
Name: helix-ai
Version: 1.0.4
Author-email: Daniel Lea <Daniel.Lea@nottingham.ac.uk>, Eduardo Aguilar <pcxea2@exmail.nottingham.ac.uk>, Karthikeyan Sivakumar <psxks12@exmail.nottingham.ac.uk>, Grazziela Figueredo <pmzgf@exmail.nottingham.ac.uk>
License-File: LICENSE
Requires-Python: <3.13,>=3.11
Requires-Dist: lime==0.2.0.1
Requires-Dist: matplotlib==3.8.2
Requires-Dist: numpy==1.26.4
Requires-Dist: openpyxl>=3.1.5
Requires-Dist: pandas==2.2.2
Requires-Dist: scikit-fuzzy==0.5.0
Requires-Dist: scikit-learn==1.5.2
Requires-Dist: seaborn==0.13.2
Requires-Dist: shap==0.45.0
Requires-Dist: streamlit-aggrid<2.0.0,>=1.1.0
Requires-Dist: streamlit==1.36
Requires-Dist: torch<3.0.0,>=2.5.1; sys_platform != 'darwin' or platform_machine != 'x86_64'
Requires-Dist: torch==2.2.0; sys_platform == 'darwin' and platform_machine == 'x86_64'
Requires-Dist: tqdm==4.66.2
Requires-Dist: xgboost==2.1.0
